{
  "api": {
    "__typename": "InterfaceType",
    "fields": [],
    "id": "ee8bbcc3-ca42-4c48-8bc3-ae1cb1d7cdde",
    "kind": "InterfaceType",
    "name": "HtmlKbd API",
    "types": [
      {
        "__typename": "InterfaceType",
        "fields": [],
        "id": "ee8bbcc3-ca42-4c48-8bc3-ae1cb1d7cdde",
        "kind": "InterfaceType",
        "name": "HtmlKbd API"
      }
    ]
  },
  "atom": {
    "__typename": "Atom",
    "api": {
      "id": "ee8bbcc3-ca42-4c48-8bc3-ae1cb1d7cdde"
    },
    "externalCssSource": null,
    "externalJsSource": null,
    "externalSourceType": null,
    "icon": null,
    "id": "10567f68-be24-4bb4-9e64-1be3108c301b",
    "name": "HtmlKbd",
    "owner": {
      "id": "0147b1b3-03b2-469a-b94e-c7fe3239edda"
    },
    "requiredParents": [],
    "suggestedChildren": [],
    "tags": [
      {
        "id": "9bd43269-fdb3-4a95-b5c0-4129f8f20a75"
      }
    ],
    "type": "HtmlKbd"
  }
}
